parse_wkb/__init__.py
parse_wkb/_impl/geojson_to_wkb.py
parse_wkb/_impl/wkb_to_abstract.py
parse_wkb/_impl/wkb_to_geojson.py
parse_wkb/_impl/wkb_to_wkt.py
parse_wkb-1.0.0.dist-info/METADATA
parse_wkb-1.0.0.dist-info/WHEEL
parse_wkb-1.0.0.dist-info/RECORD
