Metadata-Version: 2.1
Name: parse-wkb
Version: 1.0.0
Summary: Pure python library to parse WKB (Well Known Binary) GIS geospatial geometry format
Project-URL: Documentation, https://github.com/thehappycheese/parse-wkb#readme
Project-URL: Issues, https://github.com/thehappycheese/parse-wkb/issues
Project-URL: Source, https://github.com/thehappycheese/parse-wkb
Author: thehappycheese
License-Expression: MIT
Requires-Python: >=3.8
